hpe/__init__.py
hpe/cli.py
hpe/code/hpe.py
hpe-2.3.5.dist-info/licenses/LICENSE
hpe-2.3.5.dist-info/METADATA
hpe-2.3.5.dist-info/WHEEL
hpe-2.3.5.dist-info/entry_points.txt
hpe-2.3.5.dist-info/top_level.txt
hpe-2.3.5.dist-info/RECORD
