Metadata-Version: 2.4
Name: hpe
Version: 2.3.5
Summary: Hamid Py Engine
Author: Alireza Enhessari
Author-email: "S.U.P.E" <hamedsheygh3130011@gmail.com>
License: Custom License
Project-URL: Homepage, https://github.com/lolgg313/HPE
Project-URL: Repository, https://github.com/lolgg313/HPE
Project-URL: Issues, https://github.com/lolgg313/HPE/issues
Classifier: Development Status :: 4 - Beta
Classifier: Intended Audience :: Developers
Classifier: License :: OSI Approved :: MIT License
Classifier: Operating System :: OS Independent
Classifier: Programming Language :: Python :: 3.8
Classifier: Programming Language :: Python :: 3.9
Classifier: Programming Language :: Python :: 3.10
Classifier: Programming Language :: Python :: 3.11
Classifier: Topic :: Software Development :: Build Tools
Classifier: Topic :: Games/Entertainment :: Simulation
Requires-Python: >=3.8
License-File: LICENSE
Requires-Dist: customtkinter==5.2.2
Requires-Dist: darkdetect==0.8.0
Requires-Dist: llvmlite==0.44.0
Requires-Dist: numba==0.61.2
Requires-Dist: numpy==2.2.6
Requires-Dist: packaging==25.0
Requires-Dist: pillow==11.3.0
Requires-Dist: pygame==2.6.1
Requires-Dist: PyOpenGL==3.1.9
Requires-Dist: pyopengltk==0.0.4
Requires-Dist: toml==0.10.2
Requires-Dist: trimesh==4.7.1
Requires-Dist: rtree==1.4.1
Dynamic: license-file
Dynamic: requires-python
